{
  "required": true,
  "minVersion": "0.8",
  "package": "dev.auxves.vibes.mixin",
  "compatibilityLevel": "JAVA_17",
  "server": [],
  "client": [],
  "mixins": [
    "AbstractFurnaceBlockEntityMixin",
    "BlockMixin",
    "EnderChestInventoryAccessor",
    "HopperBlockEntityMixin",
    "ItemDispenserBehaviorMixin",
    "ItemEntityMixin",
    "ItemFrameEntityMixin",
    "JukeboxBlockEntityMixin",
    "LootableContainerBlockEntityMixin",
    "PlayerEntityMixin",
    "PlayerInventoryMixin",
    "ShulkerBoxBlockMixin",
    "SimpleInventoryMixin",
    "SoundManagerAccessor",
    "SoundSystemAccessor",
    "StorageMinecartEntityMixin"
  ],
  "injectors": {
    "defaultRequire": 1
  }
}
